[
  { "id": "sc_001", "text": "Healing begins the moment you stop rushing your own heart, {name}.", "gender": "female" },
  { "id": "sc_002", "text": "Softness returns to me as I release what no longer feels like home.", "gender": "female" },
  { "id": "sc_003", "text": "Calm rises inside me while I rebuild myself with patience.", "gender": "any" },
  { "id": "sc_004", "text": "My inner world becomes lighter each time I choose to let go.", "gender": "female" },
  { "id": "sc_005", "text": "You are safe to open your heart slowly, {name}, and grow again.", "gender": "female" },
  { "id": "sc_006", "text": "Stillness brings clarity to wounds I once ignored.", "gender": "female" },
  { "id": "sc_007", "text": "My strength deepens as I learn to soften without fear.", "gender": "female" },
  { "id": "sc_008", "text": "I release the weight of old stories and make space for new beginnings.", "gender": "female" },
  { "id": "sc_009", "text": "Peace settles into me with every breath I allow myself to take fully.", "gender": "any" },
  { "id": "sc_010", "text": "Your heart is learning to trust the softness it once protected so fiercely, {name}.", "gender": "female" },
  { "id": "sc_011", "text": "I mend myself gently, without expecting perfection from my past.", "gender": "male" },
  { "id": "sc_012", "text": "Healing grows in me as I choose calm over reaction.", "gender": "male" },
  { "id": "sc_013", "text": "I allow old tension to dissolve so new clarity can rise.", "gender": "male" },
  { "id": "sc_014", "text": "My spirit becomes stronger when I stop carrying emotions that were never mine to hold.", "gender": "female" },
  { "id": "sc_015", "text": "Gentler days begin to meet you, {name}, when your heart finally breathes freely again.", "gender": "female" },
  { "id": "sc_016", "text": "Stillness helps me reconnect with the parts of me I’ve neglected.", "gender": "any" },
  { "id": "sc_017", "text": "My healing does not need to be loud; it only needs to be honest.", "gender": "female" },
  { "id": "sc_018", "text": "I honor the slow rebuilding taking place beneath the surface.", "gender": "female" },
  { "id": "sc_019", "text": "Peace grows in me each time I choose release instead of resistance.", "gender": "female" },
  { "id": "sc_020", "text": "You soften beautifully, {name}, each time you forgive the versions of yourself that didn’t know better.", "gender": "female" },
  { "id": "sc_021", "text": "I allow clarity to replace the heaviness I once carried quietly.", "gender": "any" },
  { "id": "sc_022", "text": "My emotional wounds lose power as I stop feeding them old narratives.", "gender": "female" },
  { "id": "sc_023", "text": "I embrace the slow unfolding of a version of myself that feels whole.", "gender": "female" },
  { "id": "sc_024", "text": "Growth finds me when I finally choose softness over self-blame.", "gender": "female" },
  { "id": "sc_025", "text": "A new chapter opens for you, {name}, filled with peace, clarity, and emotional freedom.", "gender": "female" },
  { "id": "sc_026", "text": "Softness returns to me as I loosen my grip on old pain.", "gender": "female" },
  { "id": "sc_027", "text": "I allow healing to unfold quietly, without forcing a timeline.", "gender": "female" },
  { "id": "sc_028", "text": "Calm energy rises in me the moment I stop reliving old wounds.", "gender": "any" },
  { "id": "sc_029", "text": "My heart becomes steadier when I choose release instead of resentment.", "gender": "female" },
  { "id": "sc_030", "text": "I welcome gentle clarity that replaces emotional noise with truth.", "gender": "female" },
  { "id": "sc_031", "text": "Deep rest supports my healing more than pressure ever will.", "gender": "female" },
  { "id": "sc_032", "text": "My spirit rises each time I forgive the parts of me that didn’t know better.", "gender": "female" },
  { "id": "sc_033", "text": "You no longer need survival mode, {name}; softness is finally safe for you now.", "gender": "female" },
  { "id": "sc_034", "text": "My emotions settle when I stop fighting their presence.", "gender": "female" },
  { "id": "sc_035", "text": "I allow tenderness to guide me back to myself without fear.", "gender": "female" },
  { "id": "sc_036", "text": "I release tension slowly, letting my breath rebuild my balance.", "gender": "male" },
  { "id": "sc_037", "text": "Calm grows inside me when I choose reflection over reaction.", "gender": "male" },
  { "id": "sc_038", "text": "I allow old patterns to fall away so new strength can rise.", "gender": "male" },
  { "id": "sc_039", "text": "You don’t need to apologize for needing time to heal, {name}.", "gender": "female" },
  { "id": "sc_040", "text": "I welcome a softer version of life where I no longer carry everything alone.", "gender": "female" },
  { "id": "sc_041", "text": "Stillness gives me space to hear what my soul has been trying to say.", "gender": "any" },
  { "id": "sc_042", "text": "My healing deepens every time I choose honesty over avoidance.", "gender": "female" },
  { "id": "sc_043", "text": "I allow emotional release to move through me without judgment.", "gender": "female" },
  { "id": "sc_044", "text": "Your limits are sacred, {name}, and honoring them strengthens you.", "gender": "female" },
  { "id": "sc_045", "text": "I move forward with clarity now that I’m no longer carrying old weight.", "gender": "female" },
  { "id": "sc_046", "text": "My peace returns each time I stop fighting the past.", "gender": "female" },
  { "id": "sc_047", "text": "I embrace the quiet courage that healing asks of me.", "gender": "female" },
  { "id": "sc_048", "text": "Your softness is becoming your strength, {name}.", "gender": "female" },
  { "id": "sc_049", "text": "I release emotional noise so truth can rise clearly inside me.", "gender": "any" },
  { "id": "sc_050", "text": "My healing is not linear, but it is real, steady, and deeply mine.", "gender": "female" },
  { "id": "sc_051", "text": "Softness returns to me when I stop demanding strength from tired parts of myself.", "gender": "female" },
  { "id": "sc_052", "text": "I allow old wounds to unclench as I breathe with more intention.", "gender": "female" },
  { "id": "sc_053", "text": "The moment you stop replaying old stories, {name}, calm rises within you.", "gender": "any" },
  { "id": "sc_054", "text": "My heart becomes lighter as I gently release the weight of past versions of myself.", "gender": "female" },
  { "id": "sc_055", "text": "I welcome clarity that meets me only when I stop rushing through my pain.", "gender": "female" },
  { "id": "sc_056", "text": "Stillness helps me notice the places where I am finally beginning to soften.", "gender": "female" },
  { "id": "sc_057", "text": "I choose release instead of repeating old patterns that held me in place.", "gender": "female" },
  { "id": "sc_058", "text": "My spirit grows clearer when I let myself feel deeply instead of hiding it.", "gender": "female" },

  { "id": "sc_059", "text": "New peace finds you, {name}, when you surrender the places that once held tension.", "gender": "female" },

  { "id": "sc_060", "text": "Gentle progress is still progress, and I honor every quiet shift.", "gender": "female" },
  { "id": "sc_061", "text": "I release emotional weight slowly, trusting the steadiness of real healing.", "gender": "male" },
  { "id": "sc_062", "text": "Calm strengthens me when I allow my breath to guide me forward.", "gender": "male" },
  { "id": "sc_063", "text": "I let old habits fade so healthier patterns can take root.", "gender": "male" },

  { "id": "sc_064", "text": "Your heart softens beautifully, {name}, when you allow yourself to rest.", "gender": "female" },

  { "id": "sc_065", "text": "I welcome a quiet kind of strength that grows from deep self-awareness.", "gender": "female" },
  { "id": "sc_066", "text": "Stillness helps me reconnect with the truth hiding beneath old hurt.", "gender": "any" },
  { "id": "sc_067", "text": "My healing deepens when I choose gentleness instead of self-punishment.", "gender": "female" },
  { "id": "sc_068", "text": "I honor my boundaries because they were built from hard lessons.", "gender": "female" },
  { "id": "sc_069", "text": "Peace meets you the moment you stop carrying burdens that were never yours, {name}.", "gender": "female" },
  { "id": "sc_070", "text": "My softness is no longer something I hide; it is something I protect.", "gender": "female" },
  { "id": "sc_071", "text": "I allow emotional release to move through me at the rhythm my heart needs.", "gender": "female" },
  { "id": "sc_072", "text": "My inner world becomes brighter when I stop feeding old fears.", "gender": "female" },
  { "id": "sc_073", "text": "I embrace the slow, honest, beautifully imperfect process of becoming whole again.", "gender": "female" },
  { "id": "sc_074", "text": "{name}, growth finds you the moment you release what drains your energy.", "gender": "any" },
  { "id": "sc_075", "text": "My healing belongs entirely to me, and it unfolds in its own powerful way.", "gender": "female" },
  { "id": "sc_076", "text": "Softness rises within me each time I choose peace over pressure.", "gender": "female" },
  { "id": "sc_077", "text": "I allow my heart to loosen its grip on moments that hurt me.", "gender": "female" },
  { "id": "sc_078", "text": "Calm settles in when I stop forcing my emotions to make sense immediately.", "gender": "any" },
  { "id": "sc_079", "text": "My healing grows stronger when I trust the small shifts I feel inside.", "gender": "female" },
  { "id": "sc_080", "text": "Gentler days begin to rise for you, {name}, when you finally honor your softness.", "gender": "female" },
  { "id": "sc_081", "text": "Stillness restores parts of me I didn’t realize were exhausted.", "gender": "female" },
  { "id": "sc_082", "text": "I breathe deeper now that I’m no longer fighting my own emotions.", "gender": "female" },
  { "id": "sc_083", "text": "My spirit becomes clearer as I practice letting go without fear.", "gender": "female" },
  { "id": "sc_084", "text": "I create space for healing by choosing rest instead of resistance.", "gender": "female" },
  { "id": "sc_085", "text": "Peace meets you softly, {name}, when you stop replaying what cannot be changed.", "gender": "female" },
  { "id": "sc_086", "text": "I release old heaviness slowly, trusting the process more each day.", "gender": "male" },
  { "id": "sc_087", "text": "Calm guides me when I respond with patience instead of judgment.", "gender": "male" },
  { "id": "sc_088", "text": "I allow room for growth by letting outdated patterns fall away.", "gender": "male" },
  { "id": "sc_089", "text": "Your heart grows softer, {name}, as you learn to hold yourself with compassion.", "gender": "female" },
  { "id": "sc_090", "text": "I welcome a new chapter where I don’t have to carry every burden alone.", "gender": "female" },
  { "id": "sc_091", "text": "Stillness helps me hear the truth beneath all the noise I’ve been carrying.", "gender": "any" },
  { "id": "sc_092", "text": "Your healing deepens the moment you stop apologizing for needing time, {name}.", "gender": "female" },
  { "id": "sc_093", "text": "I allow emotional release to move through me without fear or shame.", "gender": "female" },
  { "id": "sc_094", "text": "My inner strength grows every time I choose to rest instead of push.", "gender": "female" },
  { "id": "sc_095", "text": "I release old narratives so my heart can finally breathe freely.", "gender": "female" },

  { "id": "sc_096", "text": "Your peace becomes louder, {name}, when you stop feeding what drains you.", "gender": "female" },

  { "id": "sc_097", "text": "I embrace the rebuilding happening inside me, even when I can’t see it fully.", "gender": "female" },
  { "id": "sc_098", "text": "My softness is powerful, and it helps me heal in ways force never could.", "gender": "female" },
  { "id": "sc_099", "text": "I trust the gentle unfolding of the version of me I’m becoming.", "gender": "any" },
  { "id": "sc_100", "text": "My healing is steady, honest, and beautifully aligned with who I am now.", "gender": "female" },

  { "id": "sc_101", "text": "Softness reaches you, {name}, when you finally stop resisting what your heart knows.", "gender": "female" },

  { "id": "sc_102", "text": "I allow emotional clutter to dissolve slowly as clarity returns.", "gender": "female" },
  { "id": "sc_103", "text": "Calm rises gently inside me when I let the moment be enough.", "gender": "any" },
  { "id": "sc_104", "text": "My heart grows lighter as I stop holding onto what was never meant to stay.", "gender": "female" },
  { "id": "sc_105", "text": "I welcome the kind of peace that rebuilds me from the inside out.", "gender": "female" },
  { "id": "sc_106", "text": "Stillness reveals truths I hid from myself for far too long.", "gender": "female" },
  { "id": "sc_107", "text": "I choose release even when letting go feels unfamiliar.", "gender": "female" },
  { "id": "sc_108", "text": "My energy shifts when I stop blaming myself for what I didn’t know.", "gender": "female" },
  { "id": "sc_109", "text": "I allow my breath to guide me back to calm again and again.", "gender": "female" },

  { "id": "sc_110", "text": "Peace touches you when you stop trying to control everything at once, {name}.", "gender": "female" },

  { "id": "sc_111", "text": "I soften old tension by giving myself the space I once denied.", "gender": "male" },
  { "id": "sc_112", "text": "Calm becomes easier when I let my thoughts slow down.", "gender": "male" },
  { "id": "sc_113", "text": "I allow healing to happen naturally instead of forcing change.", "gender": "male" },
  
  { "id": "sc_114", "text": "Your heart blooms quietly, {name}, as trust rebuilds inside you.", "gender": "female" },

  { "id": "sc_115", "text": "I welcome softness into places I once protected with walls.", "gender": "female" },
  { "id": "sc_116", "text": "Stillness helps me understand the emotions I once ran from.", "gender": "any" },
  { "id": "sc_117", "text": "My healing deepens with every boundary I honor without guilt.", "gender": "female" },
  { "id": "sc_118", "text": "I allow my inner world to change at the pace it truly needs.", "gender": "female" },
  { "id": "sc_119", "text": "Peace unfolds within me when I stop feeding old insecurities.", "gender": "female" },

  { "id": "sc_120", "text": "Your softness, {name}, is becoming the foundation of your new strength.", "gender": "female" },

  { "id": "sc_121", "text": "I release emotional noise so my spirit can breathe freely again.", "gender": "female" },
  { "id": "sc_122", "text": "My healing becomes more real each time I choose presence over panic.", "gender": "female" },
  { "id": "sc_123", "text": "I accept the parts of me that are still learning, still growing, still opening.", "gender": "female" },
  { "id": "sc_124", "text": "My heart steadies when I stop holding myself to impossible standards.", "gender": "any" },
  { "id": "sc_125", "text": "I allow a gentler version of life to meet me, one breath at a time.", "gender": "female" },

  { "id": "sc_126", "text": "Softness returns to you, {name}, when you stop forcing unbreakable strength.", "gender": "female" },

  { "id": "sc_127", "text": "I allow old emotions to rise and pass without clinging to their stories.", "gender": "female" },
  { "id": "sc_128", "text": "Calm meets me gently when I breathe with intention instead of fear.", "gender": "any" },
  { "id": "sc_129", "text": "My heart becomes lighter each time I choose release instead of resistance.", "gender": "female" },
  { "id": "sc_130", "text": "I welcome a softer chapter where my healing isn’t rushed or judged.", "gender": "female" },
  { "id": "sc_131", "text": "Stillness restores the parts of me that chaos once overwhelmed.", "gender": "female" },
  { "id": "sc_132", "text": "I release the emotional armor I no longer need to survive.", "gender": "female" },

  { "id": "sc_133", "text": "Your inner world strengthens, {name}, when you allow yourself to rest.", "gender": "female" },

  { "id": "sc_134", "text": "I allow clarity to replace confusion one breath at a time.", "gender": "female" },
  { "id": "sc_135", "text": "Peace finds me when I stop trying to carry every emotion alone.", "gender": "female" },

  { "id": "sc_136", "text": "Stillness lets your mind breathe again, {name}.", "gender": "male" },

  { "id": "sc_137", "text": "Calm settles into me when I allow my thoughts to soften.", "gender": "male" },
  { "id": "sc_138", "text": "I release old weight slowly, trusting that healing takes time.", "gender": "male" },

  { "id": "sc_139", "text": "Your heart opens wider, {name}, when you stop hiding what needs care.", "gender": "female" },

  { "id": "sc_140", "text": "I welcome gentle shifts that remind me I’m not stuck where I used to be.", "gender": "female" },
  { "id": "sc_141", "text": "Stillness helps me hear the emotions I’ve been suppressing.", "gender": "any" },
  { "id": "sc_142", "text": "My healing accelerates when I stop judging my sensitivity.", "gender": "female" },
  { "id": "sc_143", "text": "I allow the truth to surface without running from what it reveals.", "gender": "female" },
  { "id": "sc_144", "text": "My strength deepens every time I choose softness instead of fear.", "gender": "female" },
  { "id": "sc_145", "text": "I release tension that my body has held for far too long.", "gender": "female" },
  { "id": "sc_146", "text": "Your heart becomes clearer, {name}, when you forgive your past self.", "gender": "female" },
  { "id": "sc_147", "text": "I allow my emotions to move, flow, and settle without shame.", "gender": "female" },
  { "id": "sc_148", "text": "My spirit softens when I stop trying to outrun my own feelings.", "gender": "female" },
  { "id": "sc_149", "text": "Your strength rebuilds quietly, {name}, when you choose rest.", "gender": "any" },
  { "id": "sc_150", "text": "My healing is steady, sacred, and shaped by the love I offer myself.", "gender": "female" },
  { "id": "sc_151", "text": "Softness returns to me when I give myself permission to stop being strong all the time.", "gender": "female" },
  { "id": "sc_152", "text": "I allow layers of old pain to loosen their grip on my heart.", "gender": "female" },
  { "id": "sc_153", "text": "Peace enters your body, {name}, when you stop running from what you feel.", "gender": "any" },
  { "id": "sc_154", "text": "My peace deepens each time I choose release instead of holding on.", "gender": "female" },
  { "id": "sc_155", "text": "I welcome gentle clarity that shows me how far I've already come.", "gender": "female" },
  { "id": "sc_156", "text": "Stillness gives me room to reconnect with the softness I buried.", "gender": "female" },
  { "id": "sc_157", "text": "I create space for healing by letting my breath lead me back to myself.", "gender": "female" },
  { "id": "sc_158", "text": "You grow lighter, {name}, when you stop forcing immediate answers.", "gender": "female" },
  { "id": "sc_159", "text": "I allow peace to sit with me even on the days I feel undeserving of it.", "gender": "female" },
  { "id": "sc_160", "text": "Tenderness rises inside me as I let go of thoughts that drain my energy.", "gender": "female" },
  { "id": "sc_161", "text": "Your healing steadies, {name}, each time you release emotional heaviness.", "gender": "male" },
  { "id": "sc_162", "text": "Calm builds inside me when I stop reacting and start observing.", "gender": "male" },
  { "id": "sc_163", "text": "I allow growth to reshape parts of me I once protected too tightly.", "gender": "male" },
  { "id": "sc_164", "text": "Your heart opens wider, {name}, when you choose compassion over blame.", "gender": "female" },
  { "id": "sc_165", "text": "I welcome a quieter version of strength that doesn't require suffering.", "gender": "female" },
  { "id": "sc_166", "text": "Stillness shows me the emotions I’ve avoided, and I let them pass gently.", "gender": "any" },
  { "id": "sc_167", "text": "My healing becomes deeper when I stop apologizing for needing space.", "gender": "female" },
  { "id": "sc_168", "text": "Your mind softens its grip on old fears, {name}, when you finally exhale.", "gender": "female" },
  { "id": "sc_169", "text": "Peace grows inside me when I stop giving energy to unresolved stories.", "gender": "female" },
  { "id": "sc_170", "text": "My emotional world becomes gentler as I choose honesty over avoidance.", "gender": "female" },
  { "id": "sc_171", "text": "You rebuild quietly, {name}, beneath everything you’ve survived.", "gender": "female" },
  { "id": "sc_172", "text": "My softness is the foundation of the strength I'm stepping into now.", "gender": "female" },
  { "id": "sc_173", "text": "I honor the slow parts of healing because they teach me the most.", "gender": "female" },
  { "id": "sc_174", "text": "Stillness steadies my spirit when I stop expecting instant healing.", "gender": "any" },
  { "id": "sc_175", "text": "A warm, quiet kind of peace begins shaping your life now, {name}.", "gender": "female" },
  { "id": "sc_176", "text": "I let my heart rest from stories that no longer define me.", "gender": "female" },
  { "id": "sc_177", "text": "Calm returns to me as I soften the thoughts that once felt sharp.", "gender": "female" },
  { "id": "sc_178", "text": "I release hidden tension gently, allowing my breath to guide me.", "gender": "female" },
  { "id": "sc_179", "text": "My healing deepens when I stop rushing the parts of me still learning.", "gender": "female" },
  { "id": "sc_180", "text": "I choose softness in moments where I once demanded perfection.", "gender": "female" },

  { "id": "sc_181", "text": "Your heart becomes lighter, {name}, each time you stop carrying what isn't yours.", "gender": "female" },

  { "id": "sc_182", "text": "I welcome a quieter strength that grows from honesty, not pressure.", "gender": "female" },
  { "id": "sc_183", "text": "Stillness gives me a safe place to meet the emotions I've avoided.", "gender": "any" },
  { "id": "sc_184", "text": "I let clarity rise slowly as I stop forcing everything to make sense.", "gender": "female" },
  { "id": "sc_185", "text": "My heart softens each time I choose release instead of regret.", "gender": "female" },
  { "id": "sc_186", "text": "I allow my inner world to settle before I respond.", "gender": "female" },

  { "id": "sc_187", "text": "Peace finds you, {name}, when you finally breathe without holding back.", "gender": "female" },

  { "id": "sc_188", "text": "I trust the slow unraveling of patterns that once kept me stuck.", "gender": "female" },
  { "id": "sc_189", "text": "I allow softness to wrap around the parts of me that feel tender.", "gender": "female" },
  { "id": "sc_190", "text": "My healing becomes real the moment I stop pretending I'm unbothered.", "gender": "female" },
  { "id": "sc_191", "text": "I release the emotional armor that no longer protects me.", "gender": "female" },
  { "id": "sc_192", "text": "Calm strengthens me when I pause before believing every thought.", "gender": "female" },
  { "id": "sc_193", "text": "{name}, your healing deepens every time you honor your boundaries.", "gender": "female" },
  { "id": "sc_194", "text": "I embrace the quiet rebuilding happening beneath my tired places.", "gender": "female" },
  { "id": "sc_195", "text": "My spirit settles when I stop replaying moments that hurt me.", "gender": "female" },
  { "id": "sc_196", "text": "I welcome gentler mornings that remind me I’m still becoming.", "gender": "female" },
  { "id": "sc_197", "text": "I soften the grip of old emotions that no longer match who I am.", "gender": "female" },
  { "id": "sc_198", "text": "Stillness brings me back to my center when everything feels loud.", "gender": "female" },
  { "id": "sc_199", "text": "Your heart expands gently, {name}, each time you choose truth over fear.", "gender": "female" },
  { "id": "sc_200", "text": "I honor the slow progress that unfolds inside me without applause.", "gender": "female" }
]



